setup.py
t411cli/__init__.py
t411cli/configuration.py
t411cli/functions.py
t411cli/helpers.py
t411cli/t411cli.py
t411cli/version.py
t411cli.egg-info/PKG-INFO
t411cli.egg-info/SOURCES.txt
t411cli.egg-info/dependency_links.txt
t411cli.egg-info/entry_points.txt
t411cli.egg-info/not-zip-safe
t411cli.egg-info/requires.txt
t411cli.egg-info/top_level.txt