Metadata-Version: 1.1
Name: t411cli
Version: 0.5.2
Summary: Lightweight command line interface for T411 (french torrent website)
Home-page: https://github.com/Xide/t411cli
Author: Germain Gau
Author-email: germain.gau@gmail.com
License: THE BEER-WARE LICENSE
Platform: UNKNOWN
Classifier: Development Status :: 4 - Beta
Classifier: Intended Audience :: End Users/Desktop
Classifier: Programming Language :: Python :: 3
Classifier: Programming Language :: Python :: 3.3
Classifier: Programming Language :: Python :: 3.4
Classifier: Programming Language :: Python :: 3.5
Classifier: Topic :: Software Development :: Libraries :: Python Modules
Classifier: Programming Language :: Python
Classifier: Operating System :: Unix
